hp_cap_parser/__init__.py
hp_cap_parser/models.py
hp_cap_parser/parser.py
hp_cap_parser/parsers/__init__.py
hp_cap_parser/parsers/base.py
hp_cap_parser/parsers/documents_parser.py
hp_cap_parser/parsers/images_parser.py
hp_cap_parser/parsers/links_parser.py
hp_cap_parser/parsers/marketing_messaging_parser.py
hp_cap_parser/parsers/product_parser.py
hp_cap_parser/parsers/tech_specs_parser.py
hp_cap_parser-0.3.0.dist-info/METADATA
hp_cap_parser-0.3.0.dist-info/WHEEL
hp_cap_parser-0.3.0.dist-info/licenses/LICENSE
hp_cap_parser-0.3.0.dist-info/RECORD
