Metadata-Version: 2.4
Name: hp-cap-parser
Version: 0.3.0
Summary: A library for parsing HP Content Aggregator for Products (CAP) data
Project-URL: Homepage, https://github.com/Phalanx-Data-Labs/hp-cap-parser
Project-URL: Repository, https://github.com/Phalanx-Data-Labs/hp-cap-parser
Project-URL: Issues, https://github.com/Phalanx-Data-Labs/hp-cap-parser/issues
Author-email: Adam Bako <bakoad@gmail.com>
License: MIT
License-File: LICENSE
Classifier: Development Status :: 4 - Beta
Classifier: Intended Audience :: Developers
Classifier: License :: OSI Approved :: MIT License
Classifier: Programming Language :: Python :: 3
Classifier: Programming Language :: Python :: 3.9
Classifier: Programming Language :: Python :: 3.10
Classifier: Programming Language :: Python :: 3.11
Classifier: Programming Language :: Python :: 3.12
Classifier: Programming Language :: Python :: 3.13
Requires-Python: >=3.9
Provides-Extra: dev
Requires-Dist: pytest-cov>=4.0; extra == 'dev'
Requires-Dist: pytest>=7.0; extra == 'dev'
